menrva/__init__.py
menrva/config/__init__.py
menrva/config/_load_config.py
menrva/config/resolvers.py
menrva/logging/__init__.py
menrva/logging/mlflow/__init__.py
menrva/logging/mlflow/copy_run.py
menrva/logging/mlflow/create_run.py
menrva/logging/mlflow/diff.py
menrva/logging/mlflow/download.py
menrva/logging/mlflow/upload.py
menrva/loss/__init__.py
menrva/loss/loss_register.py
menrva/loss/torch.py
menrva/optim/__init__.py
menrva/optim/lr_register.py
menrva/optim/optim_register.py
menrva_config-0.0.1.dist-info/LICENSE
menrva_config-0.0.1.dist-info/METADATA
menrva_config-0.0.1.dist-info/WHEEL
menrva_config-0.0.1.dist-info/top_level.txt
menrva_config-0.0.1.dist-info/RECORD
