Metadata-Version: 2.2
Name: menrva-config
Version: 0.0.1
Summary: full featured deep learning training flow
Author-email: Andrea Conti <andrea.conti@tutanota.com>
License:                                  Apache License
Project-URL: Repository, https://github.com/andreaconti/menrva.git
Classifier: Programming Language :: Python :: 3
Classifier: Operating System :: OS Independent
Requires-Python: >=3.8
License-File: LICENSE
Requires-Dist: omegaconf>=2.3.0
Requires-Dist: pandas
Requires-Dist: numpy
Requires-Dist: pipe
Provides-Extra: dev
Requires-Dist: black; extra == "dev"
Requires-Dist: isort; extra == "dev"
Requires-Dist: ipython; extra == "dev"
Requires-Dist: build; extra == "dev"
Provides-Extra: test
Requires-Dist: pytest; extra == "test"
Requires-Dist: tox; extra == "test"
Provides-Extra: torch
Requires-Dist: torch>=2.0; extra == "torch"
